{
	"info": {
		"_postman_id": "5f914ab5-1a56-4880-bb73-4934a55d37e0",
		"name": "StarWars",
		"schema": "https://schema.getpostman.com/json/collection/v2.1.0/collection.json",
		"_exporter_id": "19126470"
	},
	"item": [
		{
			"name": "Peoples",
			"item": [
				{
					"name": "Get All",
					"request": {
						"method": "GET",
						"header": [],
						"url": {
							"raw": "{{base_url}}/peoples",
							"host": [
								"{{base_url}}"
							],
							"path": [
								"peoples"
							]
						}
					},
					"response": []
				},
				{
					"name": "Get One",
					"request": {
						"method": "GET",
						"header": [],
						"url": {
							"raw": "{{base_url}}/peoples/5",
							"host": [
								"{{base_url}}"
							],
							"path": [
								"peoples",
								"5"
							]
						}
					},
					"response": []
				},
				{
					"name": "Create",
					"request": {
						"method": "POST",
						"header": [],
						"body": {
							"mode": "raw",
							"raw": "{\r\n    \"name\": \"Din Djarin\",\r\n    \"gender\": \"male\",\r\n    \"skin_color\": \"fair\",\r\n    \"hair_color\": \"brown\",\r\n    \"height\": \"184\",\r\n    \"eye_color\": \"black\",\r\n    \"mass\": \"80\",\r\n    \"homeworld\": 12,\r\n    \"birth_year\": \"unknown\"\r\n}",
							"options": {
								"raw": {
									"language": "json"
								}
							}
						},
						"url": {
							"raw": "{{base_url}}/peoples",
							"host": [
								"{{base_url}}"
							],
							"path": [
								"peoples"
							]
						}
					},
					"response": []
				},
				{
					"name": "Update",
					"request": {
						"method": "PATCH",
						"header": [],
						"body": {
							"mode": "raw",
							"raw": "{\r\n    \"name\": \"Leia Skywalker\"\r\n}",
							"options": {
								"raw": {
									"language": "json"
								}
							}
						},
						"url": {
							"raw": "{{base_url}}/peoples/5",
							"host": [
								"{{base_url}}"
							],
							"path": [
								"peoples",
								"5"
							]
						}
					},
					"response": []
				},
				{
					"name": "Delete",
					"request": {
						"method": "DELETE",
						"header": [],
						"url": {
							"raw": "{{base_url}}/peoples/84",
							"host": [
								"{{base_url}}"
							],
							"path": [
								"peoples",
								"84"
							]
						}
					},
					"response": []
				}
			]
		},
		{
			"name": "Films",
			"item": [
				{
					"name": "Get All",
					"request": {
						"method": "GET",
						"header": [],
						"url": {
							"raw": "{{base_url}}/films/1",
							"host": [
								"{{base_url}}"
							],
							"path": [
								"films",
								"1"
							]
						}
					},
					"response": []
				},
				{
					"name": "Get One",
					"request": {
						"method": "GET",
						"header": [],
						"url": {
							"raw": "{{base_url}}/films/1",
							"host": [
								"{{base_url}}"
							],
							"path": [
								"films",
								"1"
							]
						}
					},
					"response": []
				},
				{
					"name": "Create",
					"request": {
						"method": "POST",
						"header": [],
						"body": {
							"mode": "raw",
							"raw": "{\r\n    \"title\": \"Force Awaken\",\r\n    \"episode_id\": 7,\r\n    \"starships\": [\r\n        2,\r\n        3,\r\n        5,\r\n        9,\r\n        10,\r\n        11,\r\n        12,\r\n        13\r\n    ],\r\n    \"vehicles\": [\r\n        4,\r\n        6,\r\n        7,\r\n        8\r\n    ],\r\n    \"planets\": [\r\n        1,\r\n        2,\r\n        3\r\n    ],\r\n    \"producer\": \"Gary Kurtz, Rick McCallum\",\r\n    \"director\": \"George Lucas\",\r\n    \"release_date\": \"1977-05-25T00:00:00.000Z\",\r\n    \"opening_crawl\": \"It is a period of civil war.\\r\\nRebel spaceships, striking\\r\\nfrom a hidden base, have won\\r\\ntheir first victory against\\r\\nthe evil Galactic Empire.\\r\\n\\r\\nDuring the battle, Rebel\\r\\nspies managed to steal secret\\r\\nplans to the Empire's\\r\\nultimate weapon, the DEATH\\r\\nSTAR, an armored space\\r\\nstation with enough power\\r\\nto destroy an entire planet.\\r\\n\\r\\nPursued by the Empire's\\r\\nsinister agents, Princess\\r\\nLeia races home aboard her\\r\\nstarship, custodian of the\\r\\nstolen plans that can save her\\r\\npeople and restore\\r\\nfreedom to the galaxy....\",\r\n    \"characters\": [\r\n        1,\r\n        2,\r\n        3,\r\n        4,\r\n        5,\r\n        6,\r\n        7,\r\n        8,\r\n        9,\r\n        10,\r\n        12,\r\n        13,\r\n        14,\r\n        15,\r\n        16,\r\n        18,\r\n        19,\r\n        81\r\n    ],\r\n    \"species\": [\r\n        1,\r\n        2,\r\n        3,\r\n        4,\r\n        5\r\n    ]\r\n}",
							"options": {
								"raw": {
									"language": "json"
								}
							}
						},
						"url": {
							"raw": "{{base_url}}/films",
							"host": [
								"{{base_url}}"
							],
							"path": [
								"films"
							]
						}
					},
					"response": []
				},
				{
					"name": "Update",
					"request": {
						"method": "PATCH",
						"header": [],
						"body": {
							"mode": "raw",
							"raw": "{\r\n    \"title\": \"Star Wars 1: A New Hope\",\r\n    \"starships\": [\r\n            31,\r\n            32,\r\n            39,\r\n            40,\r\n            41\r\n        ]\r\n}",
							"options": {
								"raw": {
									"language": "json"
								}
							}
						},
						"url": {
							"raw": "{{base_url}}/films/1",
							"host": [
								"{{base_url}}"
							],
							"path": [
								"films",
								"1"
							]
						}
					},
					"response": []
				},
				{
					"name": "Delete",
					"request": {
						"method": "DELETE",
						"header": [],
						"url": {
							"raw": "{{base_url}}/films/7",
							"host": [
								"{{base_url}}"
							],
							"path": [
								"films",
								"7"
							]
						}
					},
					"response": []
				}
			]
		},
		{
			"name": "Planets",
			"item": [
				{
					"name": "Get All",
					"request": {
						"method": "GET",
						"header": [],
						"url": {
							"raw": "{{base_url}}/planets",
							"host": [
								"{{base_url}}"
							],
							"path": [
								"planets"
							]
						}
					},
					"response": []
				},
				{
					"name": "Get One",
					"request": {
						"method": "GET",
						"header": [],
						"url": {
							"raw": "{{base_url}}/planets/1",
							"host": [
								"{{base_url}}"
							],
							"path": [
								"planets",
								"1"
							]
						}
					},
					"response": []
				},
				{
					"name": "Create",
					"request": {
						"method": "POST",
						"header": [],
						"body": {
							"mode": "raw",
							"raw": "{\r\n    \"climate\": \"humid\",\r\n    \"surface_water\": \"1\",\r\n    \"name\": \"Terre\",\r\n    \"diameter\": \"10465\",\r\n    \"rotation_period\": \"23\",\r\n    \"terrain\": \"desert\",\r\n    \"gravity\": \"1 standard\",\r\n    \"orbital_period\": \"304\",\r\n    \"population\": \"6000000\"\r\n}",
							"options": {
								"raw": {
									"language": "json"
								}
							}
						},
						"url": {
							"raw": "{{base_url}}/planets",
							"host": [
								"{{base_url}}"
							],
							"path": [
								"planets"
							]
						}
					},
					"response": []
				},
				{
					"name": "Update",
					"request": {
						"method": "PATCH",
						"header": [],
						"body": {
							"mode": "raw",
							"raw": "{\r\n    \"population\": \"200000\"\r\n}",
							"options": {
								"raw": {
									"language": "json"
								}
							}
						},
						"url": {
							"raw": "{{base_url}}/planets/1",
							"host": [
								"{{base_url}}"
							],
							"path": [
								"planets",
								"1"
							]
						}
					},
					"response": []
				},
				{
					"name": "Delete",
					"request": {
						"method": "DELETE",
						"header": [],
						"url": {
							"raw": "{{base_url}}/planets/61",
							"host": [
								"{{base_url}}"
							],
							"path": [
								"planets",
								"61"
							]
						}
					},
					"response": []
				}
			]
		},
		{
			"name": "Species",
			"item": [
				{
					"name": "Get All",
					"request": {
						"method": "GET",
						"header": [],
						"url": {
							"raw": "{{base_url}}/Species",
							"host": [
								"{{base_url}}"
							],
							"path": [
								"Species"
							]
						}
					},
					"response": []
				},
				{
					"name": "Get One",
					"request": {
						"method": "GET",
						"header": [],
						"url": {
							"raw": "{{base_url}}/species/1",
							"host": [
								"{{base_url}}"
							],
							"path": [
								"species",
								"1"
							]
						}
					},
					"response": []
				},
				{
					"name": "Create",
					"request": {
						"method": "POST",
						"header": [],
						"body": {
							"mode": "raw",
							"raw": "{\r\n    \"classification\": \"mammal\",\r\n    \"name\": \"Mandalorian\",\r\n    \"designation\": \"sentient\",\r\n    \"eye_colors\": \"black, brown, blue, green, hazel, grey, amber\",\r\n    \"people\": [\r\n        1,\r\n        4,\r\n        5,\r\n        6,\r\n        7,\r\n        9,\r\n        10,\r\n        11,\r\n        12,\r\n        14,\r\n        18,\r\n        19,\r\n        21,\r\n        22,\r\n        25,\r\n        26,\r\n        28,\r\n        29,\r\n        32,\r\n        34,\r\n        35,\r\n        39,\r\n        42,\r\n        43,\r\n        51,\r\n        60,\r\n        61,\r\n        62,\r\n        66,\r\n        67,\r\n        68,\r\n        69,\r\n        74,\r\n        81,\r\n        82\r\n    ],\r\n    \"skin_colors\": \"caucasian, black, asian, hispanic\",\r\n    \"language\": \"Galactic Basic\",\r\n    \"hair_colors\": \"blonde, brown, black, red\",\r\n    \"homeworld\": 9,\r\n    \"average_lifespan\": \"120\",\r\n    \"average_height\": \"180\"\r\n}",
							"options": {
								"raw": {
									"language": "json"
								}
							}
						},
						"url": {
							"raw": "{{base_url}}/species",
							"host": [
								"{{base_url}}"
							],
							"path": [
								"species"
							]
						}
					},
					"response": []
				},
				{
					"name": "Update",
					"request": {
						"method": "PATCH",
						"header": [],
						"body": {
							"mode": "raw",
							"raw": "{\r\n    \"eye_colors\": \"black, brown, blue, green, hazel, grey, amber\",\r\n    \"people\": [\r\n        1,\r\n        4,\r\n        5,\r\n        6,\r\n        7,\r\n        9,\r\n        10,\r\n        11,\r\n        12,\r\n        14,\r\n        18,\r\n        19,\r\n        21,\r\n        22,\r\n        25,\r\n        26,\r\n        28,\r\n        29,\r\n        32,\r\n        34,\r\n        35,\r\n        39,\r\n        42,\r\n        43,\r\n        51,\r\n        60,\r\n        61,\r\n        62,\r\n        66,\r\n        67,\r\n        68,\r\n        69,\r\n        74,\r\n        81,\r\n        82\r\n    ]\r\n}",
							"options": {
								"raw": {
									"language": "json"
								}
							}
						},
						"url": {
							"raw": "{{base_url}}/species/1",
							"host": [
								"{{base_url}}"
							],
							"path": [
								"species",
								"1"
							]
						}
					},
					"response": []
				},
				{
					"name": "Delete",
					"request": {
						"method": "DELETE",
						"header": [],
						"url": {
							"raw": "{{base_url}}/species/38",
							"host": [
								"{{base_url}}"
							],
							"path": [
								"species",
								"38"
							]
						}
					},
					"response": []
				}
			]
		},
		{
			"name": "Starships",
			"item": [
				{
					"name": "Get All",
					"request": {
						"method": "GET",
						"header": [],
						"url": {
							"raw": "{{base_url}}/starships",
							"host": [
								"{{base_url}}"
							],
							"path": [
								"starships"
							]
						}
					},
					"response": []
				},
				{
					"name": "Get One",
					"request": {
						"method": "GET",
						"header": [],
						"url": {
							"raw": "{{base_url}}/starships/2",
							"host": [
								"{{base_url}}"
							],
							"path": [
								"starships",
								"2"
							]
						}
					},
					"response": []
				},
				{
					"name": "Create",
					"request": {
						"method": "POST",
						"header": [],
						"body": {
							"mode": "raw",
							"raw": "{\r\n    \"pilots\": [\r\n        1\r\n    ],\r\n    \"MGLT\": \"60\",\r\n    \"starship_class\": \"N-1 starfighter\",\r\n    \"hyperdrive_rating\": \"5.0\"\r\n}",
							"options": {
								"raw": {
									"language": "json"
								}
							}
						},
						"url": {
							"raw": "{{base_url}}/starships",
							"host": [
								"{{base_url}}"
							],
							"path": [
								"starships"
							]
						}
					},
					"response": []
				},
				{
					"name": "Update",
					"request": {
						"method": "PATCH",
						"header": [],
						"body": {
							"mode": "raw",
							"raw": "{\r\n    \"hyperdrive_rating\": \"1.0\",\r\n    \"pilots\": [\r\n        1\r\n    ]\r\n}",
							"options": {
								"raw": {
									"language": "json"
								}
							}
						},
						"url": {
							"raw": "{{base_url}}/starships/2",
							"host": [
								"{{base_url}}"
							],
							"path": [
								"starships",
								"2"
							]
						}
					},
					"response": []
				},
				{
					"name": "Delete",
					"request": {
						"method": "DELETE",
						"header": [],
						"url": {
							"raw": "{{base_url}}/starships/76",
							"host": [
								"{{base_url}}"
							],
							"path": [
								"starships",
								"76"
							]
						}
					},
					"response": []
				}
			]
		},
		{
			"name": "Transports",
			"item": [
				{
					"name": "Get All",
					"request": {
						"method": "GET",
						"header": [],
						"url": {
							"raw": "{{base_url}}/transports",
							"host": [
								"{{base_url}}"
							],
							"path": [
								"transports"
							]
						}
					},
					"response": []
				},
				{
					"name": "Get One",
					"request": {
						"method": "GET",
						"header": [],
						"url": {
							"raw": "{{base_url}}/transports/2",
							"host": [
								"{{base_url}}"
							],
							"path": [
								"transports",
								"2"
							]
						}
					},
					"response": []
				},
				{
					"name": "Create",
					"request": {
						"method": "POST",
						"header": [],
						"body": {
							"mode": "raw",
							"raw": "{\r\n    \"consumables\": \"1 year\",\r\n    \"name\": \"CR103 corvette\",\r\n    \"cargo_capacity\": \"5000000\",\r\n    \"passengers\": \"600\",\r\n    \"max_atmosphering_speed\": \"950\",\r\n    \"crew\": \"30-165\",\r\n    \"length\": \"150\",\r\n    \"model\": \"CR90 corvette\",\r\n    \"cost_in_credits\": \"3500000\",\r\n    \"manufacturer\": \"Corellian Engineering Corporation\"\r\n}",
							"options": {
								"raw": {
									"language": "json"
								}
							}
						},
						"url": {
							"raw": "{{base_url}}/transports",
							"host": [
								"{{base_url}}"
							],
							"path": [
								"transports"
							]
						}
					},
					"response": []
				},
				{
					"name": "Update",
					"request": {
						"method": "PATCH",
						"header": [],
						"body": {
							"mode": "raw",
							"raw": "{\r\n    \"consumables\": \"2 years\"\r\n}",
							"options": {
								"raw": {
									"language": "json"
								}
							}
						},
						"url": {
							"raw": "{{base_url}}/transports/2",
							"host": [
								"{{base_url}}"
							],
							"path": [
								"transports",
								"2"
							]
						}
					},
					"response": []
				},
				{
					"name": "Delete",
					"request": {
						"method": "DELETE",
						"header": [],
						"url": {
							"raw": "{{base_url}}/transports/77",
							"host": [
								"{{base_url}}"
							],
							"path": [
								"transports",
								"77"
							]
						}
					},
					"response": []
				}
			]
		},
		{
			"name": "Vehicles",
			"item": [
				{
					"name": "Get All",
					"request": {
						"method": "GET",
						"header": [],
						"url": {
							"raw": "{{base_url}}/vehicles",
							"host": [
								"{{base_url}}"
							],
							"path": [
								"vehicles"
							]
						}
					},
					"response": []
				},
				{
					"name": "Get One",
					"request": {
						"method": "GET",
						"header": [],
						"url": {
							"raw": "{{base_url}}/vehicles/4",
							"host": [
								"{{base_url}}"
							],
							"path": [
								"vehicles",
								"4"
							]
						}
					},
					"response": []
				},
				{
					"name": "Create",
					"request": {
						"method": "POST",
						"header": [],
						"body": {
							"mode": "raw",
							"raw": "    {\r\n        \"vehicle_class\": \"caterpillar\",\r\n        \"pilots\": [\r\n            1\r\n        ]\r\n    }",
							"options": {
								"raw": {
									"language": "json"
								}
							}
						},
						"url": {
							"raw": "{{base_url}}/vehicles",
							"host": [
								"{{base_url}}"
							],
							"path": [
								"vehicles"
							]
						}
					},
					"response": []
				},
				{
					"name": "Update",
					"request": {
						"method": "PATCH",
						"header": [],
						"body": {
							"mode": "raw",
							"raw": "{\r\n    \"pilots\": [\r\n        1, \r\n        4\r\n    ]\r\n}",
							"options": {
								"raw": {
									"language": "json"
								}
							}
						},
						"url": {
							"raw": "{{base_url}}/vehicles/4",
							"host": [
								"{{base_url}}"
							],
							"path": [
								"vehicles",
								"4"
							]
						}
					},
					"response": []
				},
				{
					"name": "Delete",
					"request": {
						"method": "DELETE",
						"header": [],
						"url": {
							"raw": "{{base_url}}/vehicles/77",
							"host": [
								"{{base_url}}"
							],
							"path": [
								"vehicles",
								"77"
							]
						}
					},
					"response": []
				}
			]
		}
	],
	"event": [
		{
			"listen": "prerequest",
			"script": {
				"type": "text/javascript",
				"exec": [
					""
				]
			}
		},
		{
			"listen": "test",
			"script": {
				"type": "text/javascript",
				"exec": [
					""
				]
			}
		}
	],
	"variable": [
		{
			"key": "base_url",
			"value": "http://localhost:{{port}}",
			"type": "string"
		},
		{
			"key": "port",
			"value": "8080",
			"type": "string"
		}
	]
}